setty/__init__.py
setty/admin.py
setty/apps.py
setty/backend.py
setty/context_processors.py
setty/exceptions.py
setty/models.py
setty/wrapper.py
setty/migrations/0001_initial.py
setty/migrations/0002_settysettings_app_name.py
setty/migrations/__init__.py
setty/tests/__init__.py
setty/tests/settings.py
setty/tests/test_admin.py
setty/tests/test_backends.py
setty/tests/test_wrapper.py
django_setty-3.2.2.dist-info/LICENSE
django_setty-3.2.2.dist-info/METADATA
django_setty-3.2.2.dist-info/WHEEL
django_setty-3.2.2.dist-info/top_level.txt
django_setty-3.2.2.dist-info/RECORD
