Metadata-Version: 2.1
Name: django-setty
Version: 3.2.2
Summary: Django app allowing users to configure settings dynamically in the Admin screen
Home-page: https://github.com/mikeengland/django-setty
Author: Michael England
Author-email: michael.k.england@gmail.com
License: Apache License Version 2.0
Keywords: django dynamic live settings setty django-setty admin cache
Platform: UNKNOWN
Classifier: License :: OSI Approved :: Apache Software License
Classifier: Development Status :: 5 - Production/Stable
Classifier: Framework :: Django
Classifier: Intended Audience :: Developers
Classifier: Programming Language :: Python :: 3
Classifier: Topic :: Software Development :: Libraries :: Python Modules
Classifier: Operating System :: POSIX
Classifier: Operating System :: MacOS :: MacOS X
Classifier: Operating System :: Microsoft :: Windows
Requires-Dist: django
Requires-Dist: django-picklefield
Requires-Dist: python-memcached
